{
  "spectral_bat_screech": {
    "subtitle": "sounds.domixs-creatures.spectral_bat_screech",
    "sounds": [
      "domixs-creatures:spectral_bat_screech"
    ]
  },


  "eel_attack": {
    "subtitle": "sounds.domixs-creatures.eel_attack",
    "sounds": [
      "domixs-creatures:eel_attack"
    ]
  },


  "zap": {
    "subtitle": "sounds.domixs-creatures.zap",
    "sounds": [
      "domixs-creatures:zap_1",
      "domixs-creatures:zap_2"
    ]
  },

  "vine_hurt": {
    "subtitle": "sounds.domixs-creatures.vine_hurt",
    "sounds": [
      "domixs-creatures:vine_hurt"
    ]
  },

  "hippo_ambient": {
    "subtitle": "sounds.domixs-creatures.hippo_ambient",
    "sounds": [
      "domixs-creatures:hippo_ambient"
    ]
  },
  "hippo_hurt": {
    "subtitle": "sounds.domixs-creatures.hippo_hurt",
    "sounds": [
      "domixs-creatures:hippo_hurt"
    ]
  },

  "fire_salamander_hurt": {
    "subtitle": "sounds.domixs-creatures.fire_salamander_hurt",
    "sounds": [
      "domixs-creatures:fire_salamander_hurt_1",
      "domixs-creatures:fire_salamander_hurt_2"
    ]
  },
  "fire_salamander_death": {
    "subtitle": "sounds.domixs-creatures.fire_salamander_death",
    "sounds": [
      "domixs-creatures:fire_salamander_death"
    ]
  },


  "whale_ambient": {
    "subtitle": "sounds.domixs-creatures.whale_ambient",
    "sounds": [
      "domixs-creatures:whale_ambient_1",
      "domixs-creatures:whale_ambient_2"
    ]
  },
  "whale_hurt": {
    "subtitle": "sounds.domixs-creatures.whale_hurt",
    "sounds": [
      "domixs-creatures:whale_hurt"
    ]
  },
  "whale_death": {
    "subtitle": "sounds.domixs-creatures.whale_death",
    "sounds": [
      "domixs-creatures:whale_death"
    ]
  },


  "crocodile_ambient": {
    "subtitle": "sounds.domixs-creatures.crocodile_ambient",
    "sounds": [
      "domixs-creatures:crocodile_growl"
    ]
  },
  "crocodile_hurt": {
    "subtitle": "sounds.domixs-creatures.crocodile_hurt",
    "sounds": [
      "domixs-creatures:crocodile_hurt1"
    ]
  },
  "crocodile_death": {
    "subtitle": "sounds.domixs-creatures.crocodile_death",
    "sounds": [
      "domixs-creatures:crocodile_death"
    ]
  },

  "tiger_hurt": {
    "subtitle": "sounds.domixs-creatures.tiger_hurt",
    "sounds": [
      "domixs-creatures:tiger_hurt"
    ]
  }
}