{
	"format_version": "1.8.0",
	"animations": {
		"animation.butterfly.fly": {
			"loop": true,
			"animation_length": 0.3333,
			"bones": {
				"bone": {
					"rotation": {
						"0.0": {
							"vector": [0, 0, 50]
						},
						"0.1667": {
							"vector": [0, 0, -30]
						},
						"0.3333": {
							"vector": [0, 0, 50]
						}
					}
				},
				"bone2": {
					"rotation": {
						"0.0": {
							"vector": [0, 0, -50]
						},
						"0.1667": {
							"vector": [0, 0, 30]
						},
						"0.3333": {
							"vector": [0, 0, -50]
						}
					}
				},
				"bone5": {
					"position": {
						"0.0": {
							"vector": [0, 0, 0]
						},
						"0.1667": {
							"vector": [0, 0.05, 0]
						},
						"0.3333": {
							"vector": [0, 0, 0]
						}
					}
				},
				"bone6": {
					"rotation": {
						"vector": [-44.09531, -22.52101, 20.36057]
					}
				},
				"bone7": {
					"rotation": {
						"vector": [-44.09531, 22.52101, -20.36057]
					}
				}
			}
		}
	},
	"geckolib_format_version": 2
}